qrl/__init__.py
qrl/agents/__init__.py
qrl/agents/agents.py
qrl/agents/base.py
qrl/env/__init__.py
qrl/env/core/__init__.py
qrl/env/core/base__.py
qrl/env/core/bloch_sphere.py
qrl/env/core/compiler.py
qrl/env/core/error_channel.py
qrl/env/core/expressibility.py
qrl/env/core/probability.py
qrl/env/core/utils.py
qrl_qai-0.1.0.dist-info/licenses/LICENSE.txt
qrl_qai-0.1.0.dist-info/METADATA
qrl_qai-0.1.0.dist-info/WHEEL
qrl_qai-0.1.0.dist-info/top_level.txt
qrl_qai-0.1.0.dist-info/RECORD
