Metadata-Version: 2.4
Name: qrl-qai
Version: 0.1.0
Summary: Quantum Reinforcement Learning library: environments, policies and training loops with PennyLane.
Author-email: Jay Shah <jay.shah@qrlqai.com>
License: 
Project-URL: Homepage, https://github.com/Jayshah25/Quantum-Reinforcement-Learning
Project-URL: Issues, https://github.com/Jayshah25/Quantum-Reinforcement-Learning/issues
Keywords: quantum computing,reinforcement learning,pennylane,qml,rl
Classifier: Development Status :: 3 - Alpha
Classifier: Intended Audience :: Science/Research
Classifier: Topic :: Scientific/Engineering :: Artificial Intelligence
Classifier: Programming Language :: Python :: 3
Classifier: License :: OSI Approved :: Apache Software License
Classifier: Operating System :: OS Independent
Requires-Python: >=3.8
License-File: LICENSE.txt
Requires-Dist: torch==2.5.0
Requires-Dist: gymnasium<2.0,>=1.1
Requires-Dist: pygame<3.0,>=2.6
Requires-Dist: imageio<3.0,>=2.37
Requires-Dist: imageio-ffmpeg<1.0,>=0.6
Requires-Dist: moviepy<3.0,>=2.1
Requires-Dist: opencv-python<5.0,>=4.11
Requires-Dist: matplotlib==3.9.2
Requires-Dist: pennylane<0.43,>=0.42
Requires-Dist: autoray<0.7,>=0.6
Provides-Extra: dev
Requires-Dist: pytest; extra == "dev"
Requires-Dist: ruff; extra == "dev"
Requires-Dist: black; extra == "dev"
Requires-Dist: mypy; extra == "dev"
Requires-Dist: build; extra == "dev"
Requires-Dist: twine; extra == "dev"
Requires-Dist: pre-commit; extra == "dev"
Provides-Extra: docs
Requires-Dist: sphinx; extra == "docs"
Requires-Dist: furo; extra == "docs"
Requires-Dist: sphinx-autodoc-typehints; extra == "docs"
Requires-Dist: sphinx_rtd_theme; extra == "docs"
Provides-Extra: viz
Requires-Dist: matplotlib; extra == "viz"
Requires-Dist: tensorboard; extra == "viz"
Provides-Extra: examples
Requires-Dist: jupyter; extra == "examples"
Dynamic: license-file
